atomizer/__index__.py
atomizer/atomize.py
atomizer-0.0.2.dist-info/METADATA
atomizer-0.0.2.dist-info/WHEEL
atomizer-0.0.2.dist-info/entry_points.txt
atomizer-0.0.2.dist-info/top_level.txt
atomizer-0.0.2.dist-info/RECORD
